{"97b602d906fd27552496001a317cd6a2": {"01": {"URI-R": "http://web.archive.org/web/20160701010000if_/http://www.latimes.com/", "URI-M": "http://web.archive.org/web/20160701012535if_/http://www.latimes.com/", "Memento-Datetime": "Fri, 01 Jul 2016 01:25:35 GMT"}, "02": {"URI-R": "http://web.archive.org/web/20160702010000if_/http://www.latimes.com/", "URI-M": "http://web.archive.org/web/20160702011410if_/http://www.latimes.com/", "Memento-Datetime": "Sat, 02 Jul 2016 01:14:10 GMT"}, "03": {"URI-R": "http://web.archive.org/web/20160703010000if_/http://www.latimes.com/", "URI-M": "http://web.archive.org/web/20160703013043if_/http://www.latimes.com/", "Memento-Datetime": "Sun, 03 Jul 2016 01:30:43 GMT"}, "04": {"URI-R": "http://web.archive.org/web/20160704010000if_/http://www.latimes.com/", "URI-M": "http://web.archive.org/web/20160704013342if_/http://www.latimes.com/", "Memento-Datetime": "Mon, 04 Jul 2016 01:33:42 GMT"}, "05": {"URI-R": "http://web.archive.org/web/20160705010000if_/http://www.latimes.com/", "URI-M": "http://web.archive.org/web/20160705000952if_/http://www.latimes.com/", "Memento-Datetime": "Tue, 05 Jul 2016 00:09:52 GMT"}, "06": {"URI-R": "http://web.archive.org/web/20160706010000if_/http://www.latimes.com/", "URI-M": "http://web.archive.org/web/20160706004410if_/http://www.latimes.com/", "Memento-Datetime": "Wed, 06 Jul 2016 00:44:10 GMT"}, "07": {"URI-R": "http://web.archive.org/web/20160707010000if_/http://www.latimes.com/", "URI-M": "http://web.archive.org/web/20160707010709if_/http://www.latimes.com/", "Memento-Datetime": "Thu, 07 Jul 2016 01:07:09 GMT"}, "08": {"URI-R": "http://web.archive.org/web/20160708010000if_/http://www.latimes.com/", "URI-M": "http://web.archive.org/web/20160708021531if_/http://www.latimes.com/", "Memento-Datetime": "Fri, 08 Jul 2016 02:15:31 GMT"}, "09": {"URI-R": "http://web.archive.org/web/20160709010000if_/http://www.latimes.com/", "URI-M": "http://web.archive.org/web/20160709000542if_/http://www.latimes.com/", "Memento-Datetime": "Sat, 09 Jul 2016 00:05:42 GMT"}, "10": {"URI-R": "http://web.archive.org/web/20160710010000if_/http://www.latimes.com/", "URI-M": "http://web.archive.org/web/20160710001000if_/http://www.latimes.com/", "Memento-Datetime": "Sun, 10 Jul 2016 00:10:00 GMT"}, "11": {"URI-R": "http://web.archive.org/web/20160711010000if_/http://www.latimes.com/", "URI-M": "http://web.archive.org/web/20160711004957if_/http://www.latimes.com/", "Memento-Datetime": "Mon, 11 Jul 2016 00:49:57 GMT"}, "12": {"URI-R": "http://web.archive.org/web/20160712010000if_/http://www.latimes.com/", "URI-M": "http://web.archive.org/web/20160712005536if_/http://www.latimes.com/", "Memento-Datetime": "Tue, 12 Jul 2016 00:55:36 GMT"}, "13": {"URI-R": "http://web.archive.org/web/20160713010000if_/http://www.latimes.com/", "URI-M": "http://web.archive.org/web/20160713014640if_/http://www.latimes.com/", "Memento-Datetime": "Wed, 13 Jul 2016 01:46:40 GMT"}, "14": {"URI-R": "http://web.archive.org/web/20160714010000if_/http://www.latimes.com/", "URI-M": "http://web.archive.org/web/20160714012753if_/http://www.latimes.com/", "Memento-Datetime": "Thu, 14 Jul 2016 01:27:53 GMT"}, "15": {"URI-R": "http://web.archive.org/web/20160715010000if_/http://www.latimes.com/", "URI-M": "http://web.archive.org/web/20160714232151if_/http://www.latimes.com/", "Memento-Datetime": "Thu, 14 Jul 2016 23:21:51 GMT"}, "16": {"URI-R": "http://web.archive.org/web/20160716010000if_/http://www.latimes.com/", "URI-M": "http://web.archive.org/web/20160716011747if_/http://www.latimes.com/", "Memento-Datetime": "Sat, 16 Jul 2016 01:17:47 GMT"}, "17": {"URI-R": "http://web.archive.org/web/20160717010000if_/http://www.latimes.com/", "URI-M": "http://web.archive.org/web/20160716215830if_/http://www.latimes.com/", "Memento-Datetime": "Sat, 16 Jul 2016 21:58:30 GMT"}, "18": {"URI-R": "http://web.archive.org/web/20160718010000if_/http://www.latimes.com/", "URI-M": "http://web.archive.org/web/20160717215906if_/http://www.latimes.com/", "Memento-Datetime": "Sun, 17 Jul 2016 21:59:06 GMT"}, "19": {"URI-R": "http://web.archive.org/web/20160719010000if_/http://www.latimes.com/", "URI-M": "http://web.archive.org/web/20160719004246if_/http://www.latimes.com/", "Memento-Datetime": "Tue, 19 Jul 2016 00:42:46 GMT"}, "20": {"URI-R": "http://web.archive.org/web/20160720010000if_/http://www.latimes.com/", "URI-M": "http://web.archive.org/web/20160720005818if_/http://www.latimes.com/", "Memento-Datetime": "Wed, 20 Jul 2016 00:58:18 GMT"}, "21": {"URI-R": "http://web.archive.org/web/20160721010000if_/http://www.latimes.com/", "URI-M": "http://web.archive.org/web/20160721020924if_/http://www.latimes.com/", "Memento-Datetime": "Thu, 21 Jul 2016 02:09:24 GMT"}, "22": {"URI-R": "http://web.archive.org/web/20160722010000if_/http://www.latimes.com/", "URI-M": "http://web.archive.org/web/20160722000513if_/http://www.latimes.com/", "Memento-Datetime": "Fri, 22 Jul 2016 00:05:13 GMT"}, "23": {"URI-R": "http://web.archive.org/web/20160723010000if_/http://www.latimes.com/", "URI-M": "http://web.archive.org/web/20160723025544if_/http://www.latimes.com/", "Memento-Datetime": "Sat, 23 Jul 2016 02:55:44 GMT"}, "24": {"URI-R": "http://web.archive.org/web/20160724010000if_/http://www.latimes.com/", "URI-M": "http://web.archive.org/web/20160724040109if_/http://www.latimes.com:80/", "Memento-Datetime": "Sun, 24 Jul 2016 04:01:09 GMT"}, "25": {"URI-R": "http://web.archive.org/web/20160725010000if_/http://www.latimes.com/", "URI-M": "http://web.archive.org/web/20160725003225if_/http://www.latimes.com/", "Memento-Datetime": "Mon, 25 Jul 2016 00:32:25 GMT"}, "26": {"URI-R": "http://web.archive.org/web/20160726010000if_/http://www.latimes.com/", "URI-M": "http://web.archive.org/web/20160726010818if_/http://www.latimes.com/", "Memento-Datetime": "Tue, 26 Jul 2016 01:08:18 GMT"}, "27": {"URI-R": "http://web.archive.org/web/20160727010000if_/http://www.latimes.com/", "URI-M": "http://web.archive.org/web/20160727004115if_/http://www.latimes.com/", "Memento-Datetime": "Wed, 27 Jul 2016 00:41:15 GMT"}, "28": {"URI-R": "http://web.archive.org/web/20160728010000if_/http://www.latimes.com/", "URI-M": "http://web.archive.org/web/20160728011059if_/http://www.latimes.com/", "Memento-Datetime": "Thu, 28 Jul 2016 01:10:59 GMT"}, "29": {"URI-R": "http://web.archive.org/web/20160729010000if_/http://www.latimes.com/", "URI-M": "http://web.archive.org/web/20160728233203if_/http://www.latimes.com/", "Memento-Datetime": "Thu, 28 Jul 2016 23:32:03 GMT"}, "30": {"URI-R": "http://web.archive.org/web/20160730010000if_/http://www.latimes.com/", "URI-M": "http://web.archive.org/web/20160730015035if_/http://www.latimes.com/", "Memento-Datetime": "Sat, 30 Jul 2016 01:50:35 GMT"}, "31": {"URI-R": "http://web.archive.org/web/20160731010000if_/http://www.latimes.com/", "URI-M": "http://web.archive.org/web/20160731022444if_/http://www.latimes.com/", "Memento-Datetime": "Sun, 31 Jul 2016 02:24:44 GMT"}}}