{"f16dc396e088c7c707eabe9d7479e7a2": {"01": {"URI-R": "http://web.archive.org/web/20161201010000if_/https://www.washingtonpost.com/", "URI-M": "http://web.archive.org/web/20161201012925if_/https://www.washingtonpost.com/", "Memento-Datetime": "Thu, 01 Dec 2016 01:29:25 GMT"}, "02": {"URI-R": "http://web.archive.org/web/20161202010000if_/https://www.washingtonpost.com/", "URI-M": "http://web.archive.org/web/20161202005801if_/https://www.washingtonpost.com/", "Memento-Datetime": "Fri, 02 Dec 2016 00:58:01 GMT"}, "03": {"URI-R": "http://web.archive.org/web/20161203010000if_/https://www.washingtonpost.com/", "URI-M": "http://web.archive.org/web/20161203004538if_/https://www.washingtonpost.com/", "Memento-Datetime": "Sat, 03 Dec 2016 00:45:38 GMT"}, "04": {"URI-R": "http://web.archive.org/web/20161204010000if_/https://www.washingtonpost.com/", "URI-M": "http://web.archive.org/web/20161204005809if_/https://www.washingtonpost.com/", "Memento-Datetime": "Sun, 04 Dec 2016 00:58:09 GMT"}, "05": {"URI-R": "http://web.archive.org/web/20161205010000if_/https://www.washingtonpost.com/", "URI-M": "http://web.archive.org/web/20161205005624if_/https://www.washingtonpost.com/", "Memento-Datetime": "Mon, 05 Dec 2016 00:56:24 GMT"}, "06": {"URI-R": "http://web.archive.org/web/20161206010000if_/https://www.washingtonpost.com/", "URI-M": "http://web.archive.org/web/20161206005738if_/https://www.washingtonpost.com/", "Memento-Datetime": "Tue, 06 Dec 2016 00:57:38 GMT"}, "07": {"URI-R": "http://web.archive.org/web/20161207010000if_/https://www.washingtonpost.com/", "URI-M": "http://web.archive.org/web/20161207005207if_/https://www.washingtonpost.com/", "Memento-Datetime": "Wed, 07 Dec 2016 00:52:07 GMT"}, "08": {"URI-R": "http://web.archive.org/web/20161208010000if_/https://www.washingtonpost.com/", "URI-M": "http://web.archive.org/web/20161208012527if_/https://www.washingtonpost.com/", "Memento-Datetime": "Thu, 08 Dec 2016 01:25:27 GMT"}, "09": {"URI-R": "http://web.archive.org/web/20161209010000if_/https://www.washingtonpost.com/", "URI-M": "http://web.archive.org/web/20161209013139if_/https://www.washingtonpost.com/", "Memento-Datetime": "Fri, 09 Dec 2016 01:31:39 GMT"}, "10": {"URI-R": "http://web.archive.org/web/20161210010000if_/https://www.washingtonpost.com/", "URI-M": "http://web.archive.org/web/20161210010405if_/https://www.washingtonpost.com/", "Memento-Datetime": "Sat, 10 Dec 2016 01:04:05 GMT"}, "11": {"URI-R": "http://web.archive.org/web/20161211010000if_/https://www.washingtonpost.com/", "URI-M": "http://web.archive.org/web/20161211004831if_/https://www.washingtonpost.com/", "Memento-Datetime": "Sun, 11 Dec 2016 00:48:31 GMT"}, "12": {"URI-R": "http://web.archive.org/web/20161212010000if_/https://www.washingtonpost.com/", "URI-M": "http://web.archive.org/web/20161212005628if_/https://www.washingtonpost.com/", "Memento-Datetime": "Mon, 12 Dec 2016 00:56:28 GMT"}, "13": {"URI-R": "http://web.archive.org/web/20161213010000if_/https://www.washingtonpost.com/", "URI-M": "http://web.archive.org/web/20161213010101if_/https://www.washingtonpost.com/", "Memento-Datetime": "Tue, 13 Dec 2016 01:01:01 GMT"}, "14": {"URI-R": "http://web.archive.org/web/20161214010000if_/https://www.washingtonpost.com/", "URI-M": "http://web.archive.org/web/20161214005634if_/https://www.washingtonpost.com/", "Memento-Datetime": "Wed, 14 Dec 2016 00:56:34 GMT"}, "15": {"URI-R": "http://web.archive.org/web/20161215010000if_/https://www.washingtonpost.com/", "URI-M": "http://web.archive.org/web/20161215011711if_/https://www.washingtonpost.com/", "Memento-Datetime": "Thu, 15 Dec 2016 01:17:11 GMT"}, "16": {"URI-R": "http://web.archive.org/web/20161216010000if_/https://www.washingtonpost.com/", "URI-M": "http://web.archive.org/web/20161216010635if_/https://www.washingtonpost.com/", "Memento-Datetime": "Fri, 16 Dec 2016 01:06:35 GMT"}, "17": {"URI-R": "http://web.archive.org/web/20161217010000if_/https://www.washingtonpost.com/", "URI-M": "http://web.archive.org/web/20161217005733if_/https://www.washingtonpost.com/", "Memento-Datetime": "Sat, 17 Dec 2016 00:57:33 GMT"}, "18": {"URI-R": "http://web.archive.org/web/20161218010000if_/https://www.washingtonpost.com/", "URI-M": "http://web.archive.org/web/20161218005826if_/https://www.washingtonpost.com/", "Memento-Datetime": "Sun, 18 Dec 2016 00:58:26 GMT"}, "19": {"URI-R": "http://web.archive.org/web/20161219010000if_/https://www.washingtonpost.com/", "URI-M": "http://web.archive.org/web/20161219012836if_/https://www.washingtonpost.com/", "Memento-Datetime": "Mon, 19 Dec 2016 01:28:36 GMT"}, "20": {"URI-R": "http://web.archive.org/web/20161220010000if_/https://www.washingtonpost.com/", "URI-M": "http://web.archive.org/web/20161220005954if_/https://www.washingtonpost.com/", "Memento-Datetime": "Tue, 20 Dec 2016 00:59:54 GMT"}, "21": {"URI-R": "http://web.archive.org/web/20161221010000if_/https://www.washingtonpost.com/", "URI-M": "http://web.archive.org/web/20161221001859if_/https://www.washingtonpost.com/", "Memento-Datetime": "Wed, 21 Dec 2016 00:18:59 GMT"}, "22": {"URI-R": "http://web.archive.org/web/20161222010000if_/https://www.washingtonpost.com/", "URI-M": "http://web.archive.org/web/20161222013856if_/https://www.washingtonpost.com/", "Memento-Datetime": "Thu, 22 Dec 2016 01:38:56 GMT"}, "23": {"URI-R": "http://web.archive.org/web/20161223010000if_/https://www.washingtonpost.com/", "URI-M": "http://web.archive.org/web/20161223013722if_/https://www.washingtonpost.com/", "Memento-Datetime": "Fri, 23 Dec 2016 01:37:22 GMT"}, "24": {"URI-R": "http://web.archive.org/web/20161224010000if_/https://www.washingtonpost.com/", "URI-M": "http://web.archive.org/web/20161224013837if_/https://www.washingtonpost.com/", "Memento-Datetime": "Sat, 24 Dec 2016 01:38:37 GMT"}, "25": {"URI-R": "http://web.archive.org/web/20161225010000if_/https://www.washingtonpost.com/", "URI-M": "http://web.archive.org/web/20161225004744if_/https://www.washingtonpost.com/", "Memento-Datetime": "Sun, 25 Dec 2016 00:47:44 GMT"}, "26": {"URI-R": "http://web.archive.org/web/20161226010000if_/https://www.washingtonpost.com/", "URI-M": "http://web.archive.org/web/20161226012014if_/https://www.washingtonpost.com/", "Memento-Datetime": "Mon, 26 Dec 2016 01:20:14 GMT"}, "27": {"URI-R": "http://web.archive.org/web/20161227010000if_/https://www.washingtonpost.com/", "URI-M": "http://web.archive.org/web/20161227011910if_/https://www.washingtonpost.com/", "Memento-Datetime": "Tue, 27 Dec 2016 01:19:10 GMT"}, "28": {"URI-R": "http://web.archive.org/web/20161228010000if_/https://www.washingtonpost.com/", "URI-M": "http://web.archive.org/web/20161228005203if_/https://www.washingtonpost.com/", "Memento-Datetime": "Wed, 28 Dec 2016 00:52:03 GMT"}, "29": {"URI-R": "http://web.archive.org/web/20161229010000if_/https://www.washingtonpost.com/", "URI-M": "http://web.archive.org/web/20161229010210if_/https://www.washingtonpost.com/", "Memento-Datetime": "Thu, 29 Dec 2016 01:02:10 GMT"}, "30": {"URI-R": "http://web.archive.org/web/20161230010000if_/https://www.washingtonpost.com/", "URI-M": "http://web.archive.org/web/20161230011217if_/https://www.washingtonpost.com/", "Memento-Datetime": "Fri, 30 Dec 2016 01:12:17 GMT"}, "31": {"URI-R": "http://web.archive.org/web/20161231010000if_/https://www.washingtonpost.com/", "URI-M": "http://web.archive.org/web/20161231010036if_/https://www.washingtonpost.com/", "Memento-Datetime": "Sat, 31 Dec 2016 01:00:36 GMT"}}}